firexapp/__init__.py
firexapp/__main__.py
firexapp/_version.py
firexapp/application.py
firexapp/celery_manager.py
firexapp/common.py
firexapp/discovery.py
firexapp/fileregistry.py
firexapp/firex_subprocess.py
firexapp/info.py
firexapp/plugins.py
firexapp/broker_manager/__init__.py
firexapp/broker_manager/broker_factory.py
firexapp/broker_manager/redis_manager.py
firexapp/engine/__init__.py
firexapp/engine/celery.py
firexapp/engine/default_celery_config.py
firexapp/engine/firex_revoke.py
firexapp/engine/logging.py
firexapp/engine/run_controller.py
firexapp/events/__init__.py
firexapp/events/broker_event_consumer.py
firexapp/events/event_aggregator.py
firexapp/events/model.py
firexapp/reporters/__init__.py
firexapp/reporters/json_reporter.py
firexapp/submit/__init__.py
firexapp/submit/arguments.py
firexapp/submit/console.py
firexapp/submit/install_configs.py
firexapp/submit/report_trigger.py
firexapp/submit/reporting.py
firexapp/submit/shutdown.py
firexapp/submit/submit.py
firexapp/submit/tracking_service.py
firexapp/submit/uid.py
firexapp/tasks/__init__.py
firexapp/tasks/core_tasks.py
firexapp/tasks/example.py
firexapp/tasks/root_tasks.py
firexapp/testing/__init__.py
firexapp/testing/config_base.py
firexapp/testing/config_interpreter.py
firexapp/testing/coverage_plugin.py
firexapp/testing/pydev_debug_plugin.py
firexapp/testing/test_infra.py
firexapp-5.7.141.dist-info/licenses/LICENSE
firexapp-5.7.141.dist-info/METADATA
firexapp-5.7.141.dist-info/WHEEL
firexapp-5.7.141.dist-info/entry_points.txt
firexapp-5.7.141.dist-info/top_level.txt
firexapp-5.7.141.dist-info/zip-safe
firexapp-5.7.141.dist-info/RECORD
