Metadata-Version: 2.4
Name: firexapp
Version: 5.7.141
Summary: Core firex application libraries
Home-page: https://github.com/FireXStuff/firexapp
Author: Core FireX Team
Author-email: firex-dev@gmail.com
License: BSD-3-Clause
Classifier: Programming Language :: Python :: 3
Classifier: Operating System :: OS Independent
Classifier: License :: OSI Approved :: BSD License
License-File: LICENSE
Requires-Dist: distlib
Requires-Dist: firexkit
Requires-Dist: tqdm<=4.29.1
Requires-Dist: unittest-xml-reporting
Requires-Dist: redis
Requires-Dist: hiredis
Requires-Dist: celery[redis]==5.3.1
Requires-Dist: psutil
Requires-Dist: python-Levenshtein
Requires-Dist: entrypoints
Requires-Dist: colorlog==2.10.0
Requires-Dist: beautifulsoup4
Requires-Dist: detach3k
Requires-Dist: pytz
Requires-Dist: rapidfuzz==3.8.1
Provides-Extra: test
Requires-Dist: firex-keeper; extra == "test"
Provides-Extra: flame
Requires-Dist: firex-flame; extra == "flame"
Dynamic: author
Dynamic: author-email
Dynamic: classifier
Dynamic: home-page
Dynamic: license
Dynamic: license-file
Dynamic: provides-extra
Dynamic: requires-dist
Dynamic: summary
